pywinsor2/__init__.py
pywinsor2/core.py
pywinsor2/core_helpers.py
pywinsor2/utils.py
pywinsor2-0.4.3.dist-info/licenses/LICENSE
pywinsor2-0.4.3.dist-info/METADATA
pywinsor2-0.4.3.dist-info/WHEEL
pywinsor2-0.4.3.dist-info/top_level.txt
pywinsor2-0.4.3.dist-info/RECORD
