Metadata-Version: 2.4
Name: pywinsor2
Version: 0.4.3
Summary: Python implementation of Stata's winsor2 command for winsorizing and trimming data - Enhanced with 6 exclusive new features
Author-email: Bryce Wang <brycew6m@stanford.edu>
Maintainer-email: Bryce Wang <brycew6m@stanford.edu>
License-Expression: MIT
Project-URL: Homepage, https://github.com/brycewang-stanford/pywinsor2
Project-URL: Repository, https://github.com/brycewang-stanford/pywinsor2
Project-URL: Issues, https://github.com/brycewang-stanford/pywinsor2/issues
Project-URL: Documentation, https://github.com/brycewang-stanford/pywinsor2#readme
Keywords: stata,winsor,winsorize,trim,outliers,data-cleaning,pandas
Classifier: Development Status :: 4 - Beta
Classifier: Intended Audience :: Science/Research
Classifier: Operating System :: OS Independent
Classifier: Programming Language :: Python :: 3
Classifier: Programming Language :: Python :: 3.7
Classifier: Programming Language :: Python :: 3.8
Classifier: Programming Language :: Python :: 3.9
Classifier: Programming Language :: Python :: 3.10
Classifier: Programming Language :: Python :: 3.11
Classifier: Programming Language :: Python :: 3.12
Classifier: Programming Language :: Python :: 3.13
Classifier: Topic :: Scientific/Engineering
Classifier: Topic :: Scientific/Engineering :: Information Analysis
Classifier: Topic :: Software Development :: Libraries :: Python Modules
Requires-Python: >=3.7
License-File: LICENSE
Requires-Dist: pandas>=1.3.0
Requires-Dist: numpy>=1.20.0
Provides-Extra: dev
Requires-Dist: pytest>=6.0; extra == "dev"
Requires-Dist: pytest-cov>=2.0; extra == "dev"
Requires-Dist: black>=21.0; extra == "dev"
Requires-Dist: flake8>=3.8; extra == "dev"
Dynamic: license-file
